.bumpversion.cfg
.cookiecutterrc
.coveragerc
.editorconfig
.gitignore
.pre-commit-config.yaml
.readthedocs.yml
AUTHORS.rst
CHANGELOG.rst
CONTRIBUTING.rst
LICENSE
README.rst
pyproject.toml
setup.cfg
setup.py
tox.ini
.github/workflows/github-actions.yml
ci/bootstrap.py
ci/requirements.txt
ci/templates/.github/workflows/github-actions.yml
docs/authors.rst
docs/changelog.rst
docs/conf.py
docs/contributing.rst
docs/index.rst
docs/installation.rst
docs/readme.rst
docs/requirements.txt
docs/spelling_wordlist.txt
docs/usage.rst
docs/reference/index.rst
docs/reference/precision_recall_gain.rst
src/precision_recall_gain/__init__.py
src/precision_recall_gain/_classification.py
src/precision_recall_gain/prg.py
src/precision_recall_gain.egg-info/PKG-INFO
src/precision_recall_gain.egg-info/SOURCES.txt
src/precision_recall_gain.egg-info/dependency_links.txt
src/precision_recall_gain.egg-info/not-zip-safe
src/precision_recall_gain.egg-info/requires.txt
src/precision_recall_gain.egg-info/top_level.txt
tests/test_classification.py
tests/test_precision_recall_gain.py