Metadata-Version: 2.1
Name: precision-recall-gain
Version: 0.1.0
Summary: Precision-recall-gain curves for Python
Home-page: https://github.com/crypdick/precision-recall-gain
Author: Richard Decal
Author-email: public@richarddecal.com
License: MIT
Project-URL: Documentation, https://precision-recall-gain.readthedocs.io/
Project-URL: Changelog, https://precision-recall-gain.readthedocs.io/en/latest/changelog.html
Project-URL: Issue Tracker, https://github.com/crypdick/precision-recall-gain/issues
Classifier: Development Status :: 5 - Production/Stable
Classifier: Intended Audience :: Developers
Classifier: License :: OSI Approved :: BSD License
Classifier: Operating System :: Unix
Classifier: Operating System :: POSIX
Classifier: Operating System :: Microsoft :: Windows
Classifier: Programming Language :: Python
Classifier: Programming Language :: Python :: 3
Classifier: Programming Language :: Python :: 3 :: Only
Classifier: Programming Language :: Python :: 3.9
Classifier: Programming Language :: Python :: 3.10
Classifier: Programming Language :: Python :: 3.11
Classifier: Programming Language :: Python :: Implementation :: CPython
Classifier: Programming Language :: Python :: Implementation :: PyPy
Classifier: Topic :: Utilities
Requires-Python: >=3.9
License-File: LICENSE
License-File: AUTHORS.rst
Requires-Dist: scikit-learn>=1.1
